pg_nearest_city/__init__.py
pg_nearest_city/__version__.py
pg_nearest_city/base_nearest_city.py
pg_nearest_city/_async/__init__.py
pg_nearest_city/_async/nearest_city.py
pg_nearest_city/_sync/__init__.py
pg_nearest_city/_sync/nearest_city.py
pg_nearest_city/data/cities_1000_simple.txt.gz
pg_nearest_city/data/voronois.wkb.gz
pg_nearest_city/db/__init__.py
pg_nearest_city/db/iso-3166-1.csv.gz
pg_nearest_city/db/tables.py
pg_nearest_city/scripts/__init__.py
pg_nearest_city/scripts/voronoi_generator.py
pg_nearest_city-1.0.0.dist-info/METADATA
pg_nearest_city-1.0.0.dist-info/WHEEL
pg_nearest_city-1.0.0.dist-info/entry_points.txt
pg_nearest_city-1.0.0.dist-info/licenses/LICENSE.md
pg_nearest_city-1.0.0.dist-info/RECORD
