Metadata-Version: 2.4
Name: pg-nearest-city
Version: 1.0.0
Summary: Given a geopoint, find the nearest city using PostGIS (reverse geocode).
Project-URL: homepage, https://github.com/hotosm/pg-nearest-city
Project-URL: documentation, https://hotosm.github.io/pg-nearest-city
Project-URL: repository, https://github.com/hotosm/pg-nearest-city
Author: Emir Fabio Cognigni
Author-email: Sam Woodcock <sam.woodcock@hotosm.org>
License: GPL-3.0-only
License-File: LICENSE.md
Keywords: geocode,nearest,postgis,reverse,reverse-geocode
Classifier: Programming Language :: Python :: 3
Classifier: Programming Language :: Python :: 3.10
Classifier: Programming Language :: Python :: 3.11
Classifier: Programming Language :: Python :: 3.12
Classifier: Programming Language :: Python :: 3.13
Classifier: Topic :: Scientific/Engineering :: GIS
Classifier: Topic :: Utilities
Requires-Python: >=3.10
Requires-Dist: psycopg>=3.1
